typemapping/__init__.py
typemapping/compat.py
typemapping/origins.py
typemapping/py.typed
typemapping/type_check.py
typemapping/typemapping.py
typemapping-0.1.7.dist-info/licenses/LICENSE
typemapping-0.1.7.dist-info/METADATA
typemapping-0.1.7.dist-info/WHEEL
typemapping-0.1.7.dist-info/top_level.txt
typemapping-0.1.7.dist-info/RECORD
